programs_integrator/ProgramsIntegrator.png
programs_integrator/ProgramsIntegrator.py
programs_integrator/__init__.py
programs_integrator/config/ApplicationDir.py
programs_integrator/config/Config.py
programs_integrator/config/UserApplicationDir.py
programs_integrator/config/__init__.py
programs_integrator/desktoputils/DesktopEntry.py
programs_integrator/desktoputils/StructureMaker.py
programs_integrator/desktoputils/__init__.py
programs_integrator/user/ConfigDialog.py
programs_integrator/user/ConfigDialog.ui
programs_integrator/user/SelfUiLoader.py
programs_integrator/user/__init__.py
programs_integrator-0.3.data/data/share/applications/programs-integrator.desktop
programs_integrator-0.3.data/data/share/icons/programs-integrator.svg
programs_integrator-0.3.data/data/share/systemd/user/programs-integrator.service
programs_integrator-0.3.data/scripts/programs-integrator
programs_integrator-0.3.data/scripts/programs-integrator-ctl
programs_integrator-0.3.dist-info/LICENSE.txt
programs_integrator-0.3.dist-info/METADATA
programs_integrator-0.3.dist-info/WHEEL
programs_integrator-0.3.dist-info/top_level.txt
programs_integrator-0.3.dist-info/RECORD
