Metadata-Version: 2.1
Name: programs-integrator
Version: 0.3
Summary: Daemon program for dynamically generating 'Programs' directory
Home-page: https://github.com/artudi54/programs-integrator
Author: artudi54
Classifier: Programming Language :: Python :: 3
Classifier: License :: OSI Approved :: MIT License
Classifier: Operating System :: POSIX :: Linux
License-File: LICENSE.txt
Requires-Dist: numpy
Requires-Dist: pyside6
Requires-Dist: sortedcontainers
